{
  "geonach_idle": {
    "category": "hostile",
    "subtitle": "sounds.legendarycreatures.geonach_idle",
    "sounds": [
      {
        "name": "legendarycreatures:geonach_idle",
        "stream": false
      }
    ]
  },
  "geonach_hurt": {
    "category": "hostile",
    "subtitle": "sounds.legendarycreatures.geonach_hurt",
    "sounds": [
      {
        "name": "legendarycreatures:geonach_hurt",
        "stream": false
      }
    ]
  },
  "geonach_death": {
    "category": "hostile",
    "subtitle": "sounds.legendarycreatures.geonach_death",
    "sounds": [
      {
        "name": "legendarycreatures:geonach_death",
        "stream": false
      }
    ]
  },
  "mojo_step": {
    "category": "neutral",
    "subtitle": "sounds.legendarycreatures.mojo_step",
    "sounds": [
      {
        "name": "legendarycreatures:mojo_step1",
        "stream": false
      },
      {
        "name": "legendarycreatures:mojo_step2",
        "stream": false
      },
      {
        "name": "legendarycreatures:mojo_step3",
        "stream": false
      }
    ]
  },
  "mojo_death": {
    "category": "neutral",
    "subtitle": "sounds.legendarycreatures.mojo_death",
    "sounds": [
      {
        "name": "legendarycreatures:mojo_death",
        "stream": false
      }
    ]
  },
  "mojo_spawn": {
    "category": "neutral",
    "subtitle": "sounds.legendarycreatures.mojo_spawn",
    "sounds": [
      {
        "name": "legendarycreatures:mojo_spawn",
        "stream": false
      }
    ]
  },
  "mojo_idle": {
    "category": "hostile",
    "subtitle": "sounds.legendarycreatures.mojo_idle",
    "sounds": [
      {
        "name": "legendarycreatures:mojo_idle",
        "stream": false
      }
    ]
  },
  "mojo_hurt": {
    "category": "neutral",
    "subtitle": "sounds.legendarycreatures.mojo_hurt",
    "sounds": [
      {
        "name": "legendarycreatures:mojo_hurt",
        "stream": false
      }
    ]
  },
  "mojo_base_attack_hit": {
    "category": "neutral",
    "subtitle": "sounds.legendarycreatures.mojo_base_attack_hit",
    "sounds": [
      {
        "name": "legendarycreatures:mojo_base_attack_hit1",
        "stream": false
      },
      {
        "name": "legendarycreatures:mojo_base_attack_hit2",
        "stream": false
      },
      {
        "name": "legendarycreatures:mojo_base_attack_hit3",
        "stream": false
      }
    ]
  },
  "hound_hurt": {
    "category": "neutral",
    "subtitle": "sounds.legendarycreatures.hound_hurt",
    "sounds": [
      {
        "name": "legendarycreatures:hound/hurt1",
        "stream": false
      },
      {
        "name": "legendarycreatures:hound/hurt2",
        "stream": false
      },
      {
        "name": "legendarycreatures:hound/hurt3",
        "stream": false
      }
    ]
  },
  "hound_death": {
    "category": "neutral",
    "subtitle": "sounds.legendarycreatures.hound_death",
    "sounds": [
      {
        "name": "legendarycreatures:hound/death",
        "stream": false
      }
    ]
  },
  "hound_idle": {
    "category": "neutral",
    "subtitle": "sounds.legendarycreatures.hound_idle",
    "sounds": [
      {
        "name": "legendarycreatures:hound/idle",
        "stream": false
      }
    ]
  },
  "hound_step": {
    "category": "neutral",
    "subtitle": "sounds.legendarycreatures.hound_step",
    "sounds": [
      {
        "name": "legendarycreatures:hound/step1",
        "stream": false
      },
      {
        "name": "legendarycreatures:hound/step2",
        "stream": false
      },
      {
        "name": "legendarycreatures:hound/step3",
        "stream": false
      },
      {
        "name": "legendarycreatures:hound/step4",
        "stream": false
      },
      {
        "name": "legendarycreatures:hound/step5",
        "stream": false
      },
      {
        "name": "legendarycreatures:hound/step6",
        "stream": false
      }
    ]
  },
  "hound_base_attack_hit": {
    "category": "neutral",
    "subtitle": "sounds.legendarycreatures.hound_base_attack_hit",
    "sounds": [
      {
        "name": "legendarycreatures:hound/base_attack_hit",
        "stream": false
      }
    ]
  },
  "hound_root_attack": {
    "category": "neutral",
    "subtitle": "sounds.legendarycreatures.hound_root_attack",
    "sounds": [
      {
        "name": "legendarycreatures:hound/root",
        "stream": false
      }
    ]
  },
  "scarecrow_spawn": {
    "category": "hostile",
    "subtitle": "sounds.legendarycreatures.scarecrow_spawn",
    "sounds": [
      {
        "name": "legendarycreatures:scarecrow_spawn",
        "stream": false
      }
    ]
  },
  "scarecrow_death": {
    "category": "neutral",
    "subtitle": "sounds.legendarycreatures.scarecrow_death",
    "sounds": [
      {
        "name": "legendarycreatures:scarecrow_death",
        "stream": false
      }
    ]
  },
  "scarecrow_step": {
    "category": "neutral",
    "subtitle": "sounds.legendarycreatures.scarecrow_step",
    "sounds": [
      {
        "name": "legendarycreatures:scarecrow_step1",
        "stream": false
      },
      {
        "name": "legendarycreatures:scarecrow_step2",
        "stream": false
      },
      {
        "name": "legendarycreatures:scarecrow_step3",
        "stream": false
      }
    ]
  },
  "scarecrow_base_attack_hit": {
    "category": "neutral",
    "subtitle": "sounds.legendarycreatures.scarecrow_base_attack_hit",
    "sounds": [
      {
        "name": "legendarycreatures:scarecrow_base_attack_hit1",
        "stream": false
      },
      {
        "name": "legendarycreatures:scarecrow_base_attack_hit2",
        "stream": false
      },
      {
        "name": "legendarycreatures:scarecrow_base_attack_hit3",
        "stream": false
      }
    ]
  },
  "wisp_death": {
    "category": "neutral",
    "subtitle": "sounds.legendarycreatures.wisp_death",
    "sounds": [
      {
        "name": "legendarycreatures:wisp_death",
        "stream": false
      }
    ]
  },
  "wisp_idle": {
    "category": "neutral",
    "subtitle": "sounds.legendarycreatures.wisp_idle",
    "sounds": [
      {
        "name": "legendarycreatures:wisp_idle",
        "stream": false
      }
    ]
  },
  "scorpion_death": {
    "category": "neutral",
    "subtitle": "sounds.legendarycreatures.scorpion_death",
    "sounds": [
      {
        "name": "legendarycreatures:scorpion/scorpion_death",
        "stream": false
      }
    ]
  },
  "scorpion_hurt": {
    "category": "neutral",
    "subtitle": "sounds.legendarycreatures.scorpion_hurt",
    "sounds": [
      {
        "name": "legendarycreatures:scorpion/scorpion_hurt",
        "stream": false
      }
    ]
  },
  "scorpion_idle": {
    "category": "neutral",
    "subtitle": "sounds.legendarycreatures.scorpion_idle",
    "sounds": [
      {
        "name": "legendarycreatures:scorpion/scorpion_idle",
        "stream": false
      }
    ]
  },
  "scorpion_step": {
    "category": "neutral",
    "subtitle": "sounds.legendarycreatures.scorpion_step",
    "sounds": [
      {
        "name": "legendarycreatures:scorpion/scorpion_step",
        "stream": false
      }
    ]
  },
  "scorpion_claws_hit": {
    "category": "neutral",
    "subtitle": "sounds.legendarycreatures.scorpion_claws_hit",
    "sounds": [
      {
        "name": "legendarycreatures:scorpion/scorpion_claws_hit1",
        "stream": false
      },
      {
        "name": "legendarycreatures:scorpion/scorpion_claws_hit2",
        "stream": false
      },
      {
        "name": "legendarycreatures:scorpion/scorpion_claws_hit3",
        "stream": false
      }
    ]
  },
  "scorpion_tail_hit": {
    "category": "neutral",
    "subtitle": "sounds.legendarycreatures.scorpion_tail_hit",
    "sounds": [
      {
        "name": "legendarycreatures:scorpion/scorpion_tail_hit1",
        "stream": false
      },
      {
        "name": "legendarycreatures:scorpion/scorpion_tail_hit2",
        "stream": false
      },
      {
        "name": "legendarycreatures:scorpion/scorpion_tail_hit3",
        "stream": false
      }
    ]
  },
  "corpse_eater_spawn": {
    "category": "neutral",
    "subtitle": "sounds.legendarycreatures.corpse_eater_spawn",
    "sounds": [
      {
        "name": "legendarycreatures:corpse_eater/spawn",
        "stream": false
      }
    ]
  },
  "corpse_eater_death": {
    "category": "neutral",
    "subtitle": "sounds.legendarycreatures.corpse_eater_death",
    "sounds": [
      {
        "name": "legendarycreatures:corpse_eater/death",
        "stream": false
      }
    ]
  },
  "corpse_eater_hurt": {
    "category": "neutral",
    "subtitle": "sounds.legendarycreatures.corpse_eater_hurt",
    "sounds": [
      {
        "name": "legendarycreatures:corpse_eater/hurt0",
        "stream": false
      },
	  {
        "name": "legendarycreatures:corpse_eater/hurt1",
        "stream": false
      },
	  {
        "name": "legendarycreatures:corpse_eater/hurt2",
        "stream": false
      }
    ]
  },
  "corpse_eater_idle": {
    "category": "neutral",
    "subtitle": "sounds.legendarycreatures.corpse_eater_idle",
    "sounds": [
      {
        "name": "legendarycreatures:corpse_eater/idle0",
        "stream": false
      },
	  {
        "name": "legendarycreatures:corpse_eater/idle1",
        "stream": false
      },
	  {
        "name": "legendarycreatures:corpse_eater/idle2",
        "stream": false
      },
	  {
        "name": "legendarycreatures:corpse_eater/idle3",
        "stream": false
      }
    ]
  },
  "corpse_eater_step": {
    "category": "neutral",
    "subtitle": "sounds.legendarycreatures.corpse_eater_step",
    "sounds": [
      {
        "name": "legendarycreatures:corpse_eater/step0",
        "stream": false
      },
	  {
        "name": "legendarycreatures:corpse_eater/step1",
        "stream": false
      },
	  {
        "name": "legendarycreatures:corpse_eater/step2",
        "stream": false
      }
    ]
  },
  "corpse_eater_attack": {
    "category": "neutral",
    "subtitle": "sounds.legendarycreatures.corpse_eater_attack",
    "sounds": [
      {
        "name": "legendarycreatures:corpse_eater/attack",
        "stream": false
      }
    ]
  },
  "corpse_eater_attack_hit": {
    "category": "neutral",
    "subtitle": "sounds.legendarycreatures.corpse_eater_attack_hit",
    "sounds": [
      {
        "name": "legendarycreatures:corpse_eater/attack_hit",
        "stream": false
      }
    ]
  },
  "peacock_spider_step": {
    "category": "neutral",
    "subtitle": "sounds.legendarycreatures.peacock_spider_step",
    "sounds": [
      {
        "name": "legendarycreatures:peacock_spider/peacock_step1",
        "stream": false
      },
      {
        "name": "legendarycreatures:peacock_spider/peacock_step2",
        "stream": false
      }
    ]
  },
  "peacock_spider_hiss": {
    "category": "neutral",
    "subtitle": "sounds.legendarycreatures.peacock_spider_hiss",
    "sounds": [
      {
        "name": "legendarycreatures:peacock_spider/peacock_hiss1",
        "stream": false
      },
      {
        "name": "legendarycreatures:peacock_spider/peacock_hiss2",
        "stream": false
      },
      {
        "name": "legendarycreatures:peacock_spider/peacock_hiss3",
        "stream": false
      }
    ]
  },
  "peacock_spider_death": {
    "category": "neutral",
    "subtitle": "sounds.legendarycreatures.peacock_spider_death",
    "sounds": [
      {
        "name": "legendarycreatures:peacock_spider/peacock_death",
        "stream": false
      }
    ]
  },
  "peacock_spider_hurt": {
    "category": "neutral",
    "subtitle": "sounds.legendarycreatures.peacock_spider_hurt",
    "sounds": [
      {
        "name": "legendarycreatures:peacock_spider/peacock_hurt1",
        "stream": false
      }
    ]
  },
  "peacock_spider_run": {
    "category": "neutral",
    "subtitle": "sounds.legendarycreatures.peacock_spider_run",
    "sounds": [
      {
        "name": "legendarycreatures:peacock_spider/peacock_boing1",
        "stream": false
      },
      {
        "name": "legendarycreatures:peacock_spider/peacock_boing2",
        "stream": false
      },
      {
        "name": "legendarycreatures:peacock_spider/peacock_boing3",
        "stream": false
      }
    ]
  },
  "bullfrog_death": {
    "category": "neutral",
    "subtitle": "sounds.legendarycreatures.bullfrog_death",
    "sounds": [
      {
        "name": "legendarycreatures:bullfrog/frog_death",
        "stream": false
      }
    ]
  },
  "bullfrog_idle": {
    "category": "neutral",
    "subtitle": "sounds.legendarycreatures.bullfrog_idle",
    "sounds": [
      {
        "name": "legendarycreatures:bullfrog/frog_idle1",
        "stream": false
      },
      {
        "name": "legendarycreatures:bullfrog/frog_idle2",
        "stream": false
      },
      {
        "name": "legendarycreatures:bullfrog/frog_idle3",
        "stream": false
      }
    ]
  },
  "bullfrog_step": {
    "category": "neutral",
    "subtitle": "sounds.legendarycreatures.bullfrog_step",
    "sounds": [
      {
        "name": "legendarycreatures:bullfrog/frog_step1",
        "stream": false
      },
      {
        "name": "legendarycreatures:bullfrog/frog_step2",
        "stream": false
      },
      {
        "name": "legendarycreatures:bullfrog/frog_step3",
        "stream": false
      },
      {
        "name": "legendarycreatures:bullfrog/frog_step4",
        "stream": false
      }
    ]
  },
  "bullfrog_tongue_attack": {
    "category": "neutral",
    "subtitle": "sounds.legendarycreatures.bullfrog_tongue_attack",
    "sounds": [
      {
        "name": "legendarycreatures:bullfrog/frog_tongue1",
        "stream": false
      },
      {
        "name": "legendarycreatures:bullfrog/frog_tongue2",
        "stream": false
      }
    ]
  },
  "bullfrog_attack": {
    "category": "neutral",
    "subtitle": "sounds.legendarycreatures.bullfrog_attack",
    "sounds": [
      {
        "name": "legendarycreatures:bullfrog/frog_attack1",
        "stream": false
      },
      {
        "name": "legendarycreatures:bullfrog/frog_attack2",
        "stream": false
      }
    ]
  }
}